metric_config_parser/__init__.py
metric_config_parser/alert.py
metric_config_parser/analysis.py
metric_config_parser/cli.py
metric_config_parser/config.py
metric_config_parser/data_source.py
metric_config_parser/definition.py
metric_config_parser/dimension.py
metric_config_parser/errors.py
metric_config_parser/experiment.py
metric_config_parser/exposure_signal.py
metric_config_parser/function.py
metric_config_parser/metric.py
metric_config_parser/metric_group.py
metric_config_parser/monitoring.py
metric_config_parser/outcome.py
metric_config_parser/parameter.py
metric_config_parser/population.py
metric_config_parser/pre_treatment.py
metric_config_parser/project.py
metric_config_parser/segment.py
metric_config_parser/sql.py
metric_config_parser/statistic.py
metric_config_parser/util.py
metric_config_parser/templates/data_source_macros.j2
metric_config_parser/templates/data_source_query.sql
metric_config_parser/templates/metrics_query.sql
metric_config_parser/tests/__init__.py
metric_config_parser/tests/conftest.py
metric_config_parser/tests/test_alert.py
metric_config_parser/tests/test_analysis.py
metric_config_parser/tests/test_config.py
metric_config_parser/tests/test_experiment.py
metric_config_parser/tests/test_function.py
metric_config_parser/tests/test_metric.py
metric_config_parser/tests/test_monitoring.py
metric_config_parser/tests/test_outcomes.py
metric_config_parser/tests/test_parameter.py
metric_config_parser/tests/test_population.py
metric_config_parser/tests/test_project.py
metric_config_parser/tests/test_sql.py
metric_config_parser/tests/integration/test_config_integration.py
mozilla_metric_config_parser-2024.9.1.dist-info/LICENSE
mozilla_metric_config_parser-2024.9.1.dist-info/METADATA
mozilla_metric_config_parser-2024.9.1.dist-info/WHEEL
mozilla_metric_config_parser-2024.9.1.dist-info/entry_points.txt
mozilla_metric_config_parser-2024.9.1.dist-info/top_level.txt
mozilla_metric_config_parser-2024.9.1.dist-info/RECORD
